flute/_C.cpython-39-x86_64-linux-gnu.so
flute/__init__.py
flute/codegen_utils.py
flute/nf_utils.py
flute/ops.py
flute/packbits_utils.py
flute/tune.py
flute/utils.py
flute/csrc/config.hpp
flute/csrc/conversion_utils.hpp
flute/csrc/cutlass_extensions_bf16.h
flute/csrc/hadamard_transform.cpp
flute/csrc/hadamard_transform_cuda.cu
flute/csrc/marlin_utils.hpp
flute/csrc/packbits_utils.hpp
flute/csrc/qgemm.cpp
flute/csrc/qgemm_kernel.hpp
flute/csrc/qgemm_kernel_example.cu
flute/csrc/qgemm_kernel_raw_generated.cu
flute/csrc/tile_scheduler_utils.hpp
flute/data/qgemm_kernel_raw_generated_configs.pth
flute/data/qgemm_kernel_raw_tuned_configs.no-M.pth
flute/data/qgemm_kernel_raw_tuned_configs.pth
flute/integrations/__init__.py
flute/integrations/base.py
flute/integrations/bitsandbytes.py
flute/integrations/higgs.py
flute/integrations/huggingface.py
flute/integrations/learnable.py
flute/integrations/vllm.py
flute/integrations/vllm_utils.py
flute_kernel.libs/libcudart-9335f6a2.so.12.1.105
tests/__init__.py
tests/higgs.py
tests/kernel.py
tests/shapes.py
tests/vllm.py
flute_kernel-0.4.2.dist-info/LICENSE
flute_kernel-0.4.2.dist-info/METADATA
flute_kernel-0.4.2.dist-info/WHEEL
flute_kernel-0.4.2.dist-info/top_level.txt
flute_kernel-0.4.2.dist-info/RECORD
