Metadata-Version: 2.1
Name: flute-kernel
Version: 0.4.2
Summary: UNKNOWN
Home-page: UNKNOWN
License: UNKNOWN
Platform: UNKNOWN
License-File: LICENSE
Requires-Dist: ninja
Requires-Dist: wheel
Requires-Dist: jaxtyping
Requires-Dist: matplotlib
Requires-Dist: transformers
Requires-Dist: datasets
Requires-Dist: accelerate
Requires-Dist: vllm==0.7.2
Requires-Dist: bitsandbytes
